Metadata-Version: 1.0
Name: distpacktest
Version: 0.1
Summary: Gaussian distributions
Home-page: UNKNOWN
Author: Jenny Jang
Author-email: eppunijyj@gmail.com
License: UNKNOWN
Platform: UNKNOWN
